chap/commands/explain.py
chap_command_explain-0.0.3.dist-info/METADATA
chap_command_explain-0.0.3.dist-info/WHEEL
chap_command_explain-0.0.3.dist-info/top_level.txt
chap_command_explain-0.0.3.dist-info/RECORD
